afl_overseer-0.1.0.dist-info/licenses/LICENSE
src/__init__.py
src/cli.py
src/constants.py
src/models.py
src/monitor.py
src/output_terminal.py
src/parser.py
src/process.py
src/tui.py
src/utils.py
src/webserver.py
afl_overseer-0.1.0.dist-info/METADATA
afl_overseer-0.1.0.dist-info/WHEEL
afl_overseer-0.1.0.dist-info/entry_points.txt
afl_overseer-0.1.0.dist-info/top_level.txt
afl_overseer-0.1.0.dist-info/RECORD
