Metadata-Version: 2.4
Name: afl-overseer
Version: 0.1.0
Summary: Monitoring and visualization tool for AFL/AFL++ fuzzing campaigns
Author-email: kirit1193 <kirit1193@users.noreply.github.com>
Maintainer-email: kirit1193 <kirit1193@users.noreply.github.com>
License: MIT License
Project-URL: Homepage, https://github.com/kirit1193/afl-overseer
Project-URL: Repository, https://github.com/kirit1193/afl-overseer
Project-URL: Bug Tracker, https://github.com/kirit1193/afl-overseer/issues
Project-URL: Documentation, https://github.com/kirit1193/afl-overseer#readme
Keywords: afl,afl++,fuzzing,monitoring,visualization,security,testing
Classifier: Development Status :: 4 - Beta
Classifier: Intended Audience :: Developers
Classifier: Intended Audience :: Information Technology
Classifier: Intended Audience :: Science/Research
Classifier: Operating System :: POSIX :: Linux
Classifier: Operating System :: MacOS
Classifier: Operating System :: Unix
Classifier: Programming Language :: Python :: 3
Classifier: Programming Language :: Python :: 3.8
Classifier: Programming Language :: Python :: 3.9
Classifier: Programming Language :: Python :: 3.10
Classifier: Programming Language :: Python :: 3.11
Classifier: Programming Language :: Python :: 3.12
Classifier: Programming Language :: Python :: 3 :: Only
Classifier: Topic :: Security
Classifier: Topic :: Software Development :: Testing
Classifier: Topic :: System :: Monitoring
Classifier: Topic :: Utilities
Classifier: Environment :: Console
Classifier: Environment :: Web Environment
Requires-Python: >=3.8
License-File: LICENSE
Requires-Dist: click>=8.1.0
Requires-Dist: rich>=13.0.0
Requires-Dist: psutil>=5.9.0
Requires-Dist: textual>=0.40.0
Requires-Dist: aiohttp>=3.8.0
Provides-Extra: dev
Requires-Dist: pytest>=7.0.0; extra == "dev"
Requires-Dist: pytest-asyncio>=0.21.0; extra == "dev"
Requires-Dist: pytest-cov>=4.0.0; extra == "dev"
Requires-Dist: black>=23.0.0; extra == "dev"
Requires-Dist: flake8>=6.0.0; extra == "dev"
Requires-Dist: mypy>=1.0.0; extra == "dev"
Requires-Dist: isort>=5.12.0; extra == "dev"
Dynamic: license-file
